setup.py
VirusTotalApi3/__init__.py
VirusTotalApi3/utils.py
VirusTotalApi3.egg-info/PKG-INFO
VirusTotalApi3.egg-info/SOURCES.txt
VirusTotalApi3.egg-info/dependency_links.txt
VirusTotalApi3.egg-info/requires.txt
VirusTotalApi3.egg-info/top_level.txt