Metadata-Version: 1.0
Name: VirusTotalApi3
Version: 2020.4.16
Summary: Scan & Get Information based on API of VirusTotal API 3.0
Home-page: https://github.com/An0nimia/VirusTotalApi3
Author: An0nimia
Author-email: An0nimia@protonmail.com
License: CC BY-NC-SA 4.0
Platform: UNKNOWN
